CHANGES.rst
LICENSE.txt
MANIFEST.in
README.rst
setup.py
django_deployer/__init__.py
django_deployer/fabfile.py
django_deployer/helpers.py
django_deployer/main.py
django_deployer/providers.py
django_deployer/tasks.py
django_deployer.egg-info/PKG-INFO
django_deployer.egg-info/SOURCES.txt
django_deployer.egg-info/dependency_links.txt
django_deployer.egg-info/entry_points.txt
django_deployer.egg-info/requires.txt
django_deployer.egg-info/top_level.txt
django_deployer/paas_templates/__init__.py
django_deployer/paas_templates/wsgi.py
django_deployer/paas_templates/appengine/README.rst
django_deployer/paas_templates/appengine/__init__.py
django_deployer/paas_templates/appengine/app.yaml
django_deployer/paas_templates/appengine/manage.sh
django_deployer/paas_templates/appengine/requirements.txt
django_deployer/paas_templates/appengine/requirements_deploy.txt
django_deployer/paas_templates/appengine/settings_appengine.py
django_deployer/paas_templates/appengine/urls_appengine.py
django_deployer/paas_templates/dotcloud/README.rst
django_deployer/paas_templates/dotcloud/__init__.py
django_deployer/paas_templates/dotcloud/createdb.py
django_deployer/paas_templates/dotcloud/dotcloud.yml
django_deployer/paas_templates/dotcloud/mkadmin.py
django_deployer/paas_templates/dotcloud/nginx.conf
django_deployer/paas_templates/dotcloud/postinstall
django_deployer/paas_templates/dotcloud/requirements.txt
django_deployer/paas_templates/dotcloud/settings_dotcloud.py
django_deployer/paas_templates/dotcloud/wsgi.py
django_deployer/paas_templates/gondor/README.rst
django_deployer/paas_templates/gondor/__init__.py
django_deployer/paas_templates/gondor/gondor.yml
django_deployer/paas_templates/gondor/settings_gondor.py
django_deployer/paas_templates/stackato/README.rst
django_deployer/paas_templates/stackato/__init__.py
django_deployer/paas_templates/stackato/requirements.txt
django_deployer/paas_templates/stackato/settings_stackato.py
django_deployer/paas_templates/stackato/stackato.yml