Metadata-Version: 1.1
Name: django-deployer
Version: 0.1.6
Summary: Django deployment tool for popular PaaS providers
Home-page: http://natea.github.io/django-deployer
Author: Nate Aune
Author-email: nate@appsembler.com
License: MIT
Keywords: PaaS Django Dotcloud Stackato Heroku Gondor AWS OpenShift GAE appengine fabric deployment
Platform: UNKNOWN
Classifier: Development Status :: 3 - Alpha
Classifier: Environment :: Web Environment
Classifier: Framework :: Django
Classifier: Intended Audience :: Developers
Classifier: License :: OSI Approved :: MIT License
Classifier: Programming Language :: Python
